pulsim-0.1.11.dist-info/WHEEL
pulsim-0.1.11.dist-info/METADATA
pulsim-0.1.11.dist-info/RECORD
pulsim/_pulsim.cpython-313-x86_64-linux-gnu.so
pulsim/__init__.py
pulsim/remote/widgets.py
pulsim/remote/simulator_pb2.py
pulsim/remote/simulator_pb2_grpc.py
pulsim/remote/client.py
pulsim/remote/simulator_pb2.pyi
pulsim/remote/__init__.py
