Metadata-Version: 2.2
Name: pulsim
Version: 0.1.11
Summary: High-performance circuit simulator for power electronics
Keywords: circuit,simulation,spice,power electronics,eda
Author-Email: Pulsim Authors <pulsim@example.com>
License: MIT
Classifier: Development Status :: 3 - Alpha
Classifier: Intended Audience :: Science/Research
Classifier: Intended Audience :: Developers
Classifier: License :: OSI Approved :: MIT License
Classifier: Operating System :: OS Independent
Classifier: Programming Language :: Python :: 3
Classifier: Programming Language :: Python :: 3.8
Classifier: Programming Language :: Python :: 3.9
Classifier: Programming Language :: Python :: 3.10
Classifier: Programming Language :: Python :: 3.11
Classifier: Programming Language :: Python :: 3.12
Classifier: Programming Language :: Python :: 3.13
Classifier: Programming Language :: C++
Classifier: Topic :: Scientific/Engineering
Classifier: Topic :: Scientific/Engineering :: Electronic Design Automation (EDA)
Project-URL: Homepage, https://github.com/pulsim/pulsim-core
Project-URL: Documentation, https://pulsim.readthedocs.io
Project-URL: Repository, https://github.com/pulsim/pulsim-core
Project-URL: Issues, https://github.com/pulsim/pulsim-core/issues
Requires-Python: >=3.8
Requires-Dist: numpy>=1.20
Provides-Extra: grpc
Requires-Dist: grpcio>=1.50.0; extra == "grpc"
Requires-Dist: grpcio-tools>=1.50.0; extra == "grpc"
Requires-Dist: protobuf>=4.0.0; extra == "grpc"
Provides-Extra: jupyter
Requires-Dist: ipywidgets>=8.0; extra == "jupyter"
Requires-Dist: matplotlib>=3.5; extra == "jupyter"
Requires-Dist: plotly>=5.0; extra == "jupyter"
Provides-Extra: data
Requires-Dist: pandas>=1.3; extra == "data"
Requires-Dist: xarray>=2022.0; extra == "data"
Provides-Extra: dev
Requires-Dist: pytest>=7.0; extra == "dev"
Requires-Dist: pytest-cov>=4.0; extra == "dev"
Requires-Dist: pytest-asyncio>=0.21.0; extra == "dev"
Provides-Extra: docs
Requires-Dist: sphinx>=6.0; extra == "docs"
Requires-Dist: sphinx-rtd-theme>=1.0; extra == "docs"
Provides-Extra: all
Requires-Dist: pulsim[data,dev,grpc,jupyter]; extra == "all"
